{
  "school": "Alsikeskolan (Knivsta Kommun)",
  "message": "Varje dag serveras dagens lunch samt grönsaker, smör, bröd och mjölk/vatten. Smaklig Måltid önskar Alsikeköket!",
  "weeks": [
    [
      {
        "day": "MONDAY 09 MAR",
        "meals": {
          "Lunch": "Kyckling i currysås och jasminris",
          "Vegetariskt": "Indisk currygryta med kokosmjölk och ris",
          "Veganskt": "Indisk currygryta med kokosmjölk och ris",
          "Ej fläsk": "Kyckling i currysås och jasminris",
          "Mellanmål": "Mellanmål",
          "Frukost": "Frukost"
        }
      },
      {
        "day": "TUESDAY 10 MAR",
        "meals": {
          "Lunch": "Pannbiff med tzatsiki, varma grönsaker och klyftpotatis",
          "Vegetariskt": "Hemlagade vegetariska biffar med tzatsiki och klyftpotatis",
          "Veganskt": "Hemlagade vegetariska biffar med tzatsiki och klyftpotatis",
          "Ej fläsk": "Pannbiff med tzatsiki, varma grönsaker och klyftpotatis",
          "Mellanmål": "Mellanmål",
          "Frukost": "Frukost"
        }
      },
      {
        "day": "WEDNESDAY 11 MAR",
        "meals": {
          "Lunch": "Vegetarisk lasagne",
          "Vegetariskt": "Vegetarisk lasagne",
          "Veganskt": "Vegansk lasagne ",
          "Ej fläsk": "Vegetarisk lasagne",
          "Mellanmål": "Mellanmål",
          "Frukost": "Frukost"
        }
      },
      {
        "day": "THURSDAY 12 MAR",
        "meals": {
          "Lunch": "Köttbullar med brunsås och lingonsylt, kokt potatis",
          "Vegetariskt": "Vegobullar med brunsås, lingonsylt och kokt potatis",
          "Veganskt": "Vegobullar med brunsås, inlagd gurka och kokt potatis",
          "Ej fläsk": "Köttbullar med brunsås och lingonsylt, kokt potatis",
          "Mellanmål": "Mellanmål",
          "Frukost": "Frukost"
        }
      },
      {
        "day": "FRIDAY 13 MAR",
        "meals": {
          "Lunch": "Fiskgratäng med ost, tomat och oregano, kokt potatis",
          "Vegetariskt": "Italiensk grönsaksgratäng med ost, tomat och oregano, kokt potatis.",
          "Veganskt": "Italiensk grönsaksgratäng med ost, tomat och oregano, kokt potatis.",
          "Ej fläsk": "Fiskgratäng med ost, tomat och oregano, kokt potatis",
          "Mellanmål": "Mellanmål",
          "Frukost": "Frukost"
        }
      }
    ]
  ],
  "start_date": "2026-03-09",
  "end_date": "2026-03-15"
}